object_checker/__init__.py
object_checker/apps.py
object_checker/base_object_checker.py
object_checker/version.py
django_object_checker-1.0.2.dist-info/LICENSE
django_object_checker-1.0.2.dist-info/METADATA
django_object_checker-1.0.2.dist-info/WHEEL
django_object_checker-1.0.2.dist-info/top_level.txt
django_object_checker-1.0.2.dist-info/RECORD
