Metadata-Version: 2.1
Name: django-object-checker
Version: 1.0.2
Summary: Hello. I'm just an abstract object 📦 and I would be very glad to have user authorization because I hate criminals 🦹‍♂️ like pedophiles, robbers, hackers and so on.
Home-page: https://github.com/zurek11/django-object-checker
Author: Adam Žúrek
Author-email: adamzurek14@gmail.com
License: MIT
Platform: UNKNOWN
Classifier: Development Status :: 4 - Beta
Classifier: Programming Language :: Python
Classifier: Programming Language :: Python :: 3.5
Classifier: Programming Language :: Python :: 3.6
Classifier: Programming Language :: Python :: 3.7
Classifier: Programming Language :: Python :: 3.8
Classifier: Programming Language :: Python :: 3 :: Only
Classifier: Programming Language :: Python :: Implementation :: PyPy
Classifier: Intended Audience :: Developers
Classifier: License :: OSI Approved :: MIT License
Classifier: Topic :: Software Development :: Libraries
License-File: LICENSE
